setup.py
jiac/__init__.py
jiac/extension.py
jiac.egg-info/PKG-INFO
jiac.egg-info/SOURCES.txt
jiac.egg-info/dependency_links.txt
jiac.egg-info/requires.txt
jiac.egg-info/top_level.txt
jiac/compilers/__init__.py
jiac/compilers/javascript.py
jiac/compilers/less.py
jiac/contrib/__init__.py
jiac/contrib/flask.py