Metadata-Version: 1.1
Name: jiac
Version: 0.2.1
Summary: A Jinja extension (compatible with Flask) to compile and/or compress your assets inline.
Home-page: https://github.com/bmorgan21/jinja-inline-asset-compressor
Author: Brian Morgan
Author-email: brian.s.morgan@gmail.com
License: UNKNOWN
Platform: UNKNOWN
Classifier: Development Status :: 4 - Beta
Classifier: License :: OSI Approved :: MIT License
Classifier: Operating System :: OS Independent
